JDlibreria/Funciones.py
JDlibreria/__init__.py
jdlibreria-0.1.2.dist-info/METADATA
jdlibreria-0.1.2.dist-info/WHEEL
jdlibreria-0.1.2.dist-info/top_level.txt
jdlibreria-0.1.2.dist-info/RECORD
