Metadata-Version: 2.1
Name: JDlibreria
Version: 0.1.2
Summary: A test library
Home-page: https://github.com/JSalazar17/JDlibreria
Author: Jorge Salazar
Author-email: jisalazar@ucundinamarca.edu.co
Classifier: Programming Language :: Python :: 3
Classifier: License :: OSI Approved :: MIT License
Classifier: Operating System :: OS Independent
Requires-Python: >=3.6
Requires-Dist: numpy
